TempMail_Generator/__init__.py
TempMail_Generator/__main__.py
TempMail_Generator/config.py
TempMail_Generator/process.py
TempMail_Generator/server.py
tempmail_generator-1.0.2.dist-info/licenses/LICENSE
tempmail_generator-1.0.2.dist-info/METADATA
tempmail_generator-1.0.2.dist-info/WHEEL
tempmail_generator-1.0.2.dist-info/entry_points.txt
tempmail_generator-1.0.2.dist-info/top_level.txt
tempmail_generator-1.0.2.dist-info/RECORD
