Metadata-Version: 2.4
Name: TempMail_Generator
Version: 1.0.2
Summary: A lightweight temporary email generator built with Flask (Python) and a modern frontend. It allows you to quickly generate disposable email addresses, view incoming messages, and refresh your inbox automatically.
Home-page: https://github.com/jo0x01/TempMail-Generator
Author: Jo0x01
License: MIT
Keywords: tempmail,tmail,email,mail,temporary-email,disposable-mail
Classifier: Development Status :: 4 - Beta
Classifier: Environment :: Console
Classifier: Intended Audience :: Developers
Classifier: Programming Language :: Python :: 3
Classifier: License :: OSI Approved :: MIT License
Classifier: Operating System :: OS Independent
Requires-Python: >=3.1
License-File: LICENSE
Requires-Dist: flask
Requires-Dist: requests
Dynamic: author
Dynamic: classifier
Dynamic: description
Dynamic: description-content-type
Dynamic: home-page
Dynamic: keywords
Dynamic: license
Dynamic: license-file
Dynamic: requires-dist
Dynamic: requires-python
Dynamic: summary
